mkdocs_qr_plugin/__init__.py
mkdocs_qr_plugin/plugin.py
mkdocs_qr_plugin/qr_image_generator.py
tests/__init__.py
tests/test_plugin.py
mkdocs_qr_plugin-0.1.4.dist-info/LICENSE
mkdocs_qr_plugin-0.1.4.dist-info/METADATA
mkdocs_qr_plugin-0.1.4.dist-info/WHEEL
mkdocs_qr_plugin-0.1.4.dist-info/entry_points.txt
mkdocs_qr_plugin-0.1.4.dist-info/top_level.txt
mkdocs_qr_plugin-0.1.4.dist-info/RECORD
